scrapy_podcast_rss/__init__.py
scrapy_podcast_rss/__version__.py
scrapy_podcast_rss/exceptions.py
scrapy_podcast_rss/exporters.py
scrapy_podcast_rss/items.py
scrapy_podcast_rss/pipelines.py
scrapy_podcast_rss-0.0.3.dist-info/LICENSE
scrapy_podcast_rss-0.0.3.dist-info/METADATA
scrapy_podcast_rss-0.0.3.dist-info/WHEEL
scrapy_podcast_rss-0.0.3.dist-info/top_level.txt
scrapy_podcast_rss-0.0.3.dist-info/RECORD
