Metadata-Version: 2.1
Name: scrapy-podcast-rss
Version: 0.0.3
Summary: Scrapy pipeline and items to create and store RSS feeds for podcasts.
Home-page: https://github.com/igarizio/scrapy-podcast-rss
Author: Iacopo Garizio
Author-email: info@iacopogarizio.com
License: UNKNOWN
Platform: UNKNOWN
Classifier: Programming Language :: Python :: 3
Classifier: License :: OSI Approved :: MIT License
Classifier: Operating System :: OS Independent
Requires-Dist: Scrapy (>=1.7.3)
Requires-Dist: feedgen (==0.9.0)
Provides-Extra: s3_storage
Requires-Dist: boto3; extra == 's3_storage'
Provides-Extra: tests
Requires-Dist: pytest (==5.2.4); extra == 'tests'
